<catalog>
        <product>
            <name>Sopa</name>
            <price>1.50</price>
            <vat>0.23</vat>
        </product>
        <product>
            <name>Bifana</name>
            <price>2.00</price>
            <vat>0.23</vat>
        </product>
        <product>
            <name>Prato</name>
            <price>3.00</price>
            <vat>0.23</vat>
        </product>
        <product>
            <name>Sandes</name>
            <price>1.50</price>
            <vat>0.23</vat>
        </product>
        <product>
            <name>Cachorros</name>
            <price>1.50</price>
            <vat>0.23</vat>
        </product>
        <product>
            <name>Salgados</name>
            <price>0.80</price>
            <vat>0.23</vat>
        </product>
        <product>
            <name>Doces</name>
            <price>0.80</price>
            <vat>0.23</vat>
        </product>
        <product>
            <name>Bolos</name>
            <price>1.00</price>
            <vat>0.23</vat>
        </product>
        <product>
            <name>Fruta</name>
            <price>0.50</price>
            <vat>0.23</vat>
        </product>
        <product>
            <name>Bebidas</name>
            <price>1.00</price>
            <vat>0.23</vat>
        </product>
        <product>
            <name>Cafe</name>
            <price>0.50</price>
            <vat>0.23</vat>
        </product>
</catalog>
